KiticaAPI/__init__.py
KiticaAPI/config.py
KiticaAPI/kitica.py
KiticaAPI/sock.py
KiticaAPI/version.py
KiticaAPI/api/__init__.py
KiticaAPI/api/devicelending.py
KiticaAPI/api/devices.py
KiticaAPI/api/deviceutils.py
KiticaAPI/api/hostlistener.py
KiticaAPI/api/servers.py
KiticaAPI/api/service.py
KiticaAPI/appsocket/__init__.py
KiticaAPI/appsocket/main.py
KiticaAPI/utils/__init__.py
KiticaAPI/utils/confighelper.py
KiticaAPI/utils/configurations.py
KiticaAPI/utils/constants.py
KiticaAPI/utils/database.py
KiticaAPI/utils/database.sql
kitica-1.4a9.dist-info/METADATA
kitica-1.4a9.dist-info/WHEEL
kitica-1.4a9.dist-info/entry_points.txt
kitica-1.4a9.dist-info/top_level.txt
kitica-1.4a9.dist-info/RECORD
