Metadata-Version: 2.1
Name: kitica
Version: 1.4a9
Summary: Kitica Devicepool.
Home-page: https://github.com/MainSystemDev/kitica
Author: Joshua Kim Rivera
Author-email: joshua.rivera@mnltechnology.com
License: MIT License
Platform: any
Classifier: Development Status :: 4 - Beta
Classifier: License :: OSI Approved :: MIT License
Classifier: Operating System :: OS Independent
Classifier: Programming Language :: Python :: 3
Classifier: Topic :: Software Development :: Testing
Requires-Dist: Flask
Requires-Dist: Flask-Cors
Requires-Dist: Flask-RESTful
Requires-Dist: Flask-SocketIO
Requires-Dist: PyYAML
Requires-Dist: eventlet
Requires-Dist: flask-marshmallow
Requires-Dist: gunicorn
Requires-Dist: pycodestyle
Requires-Dist: python-socketio
Requires-Dist: webargs
